replacement/__init__.py
replacement/__main__.py
replacement-0.4.4.dist-info/LICENSE
replacement-0.4.4.dist-info/METADATA
replacement-0.4.4.dist-info/WHEEL
replacement-0.4.4.dist-info/entry_points.txt
replacement-0.4.4.dist-info/top_level.txt
replacement-0.4.4.dist-info/RECORD
