Metadata-Version: 2.1
Name: replacement
Version: 0.4.4
Summary: A tool to execute yaml templates and output text
Home-page: https://github.com/siriobalmelli/replacement
Author: Sirio Balmelli
Author-email: sirio.bm@gmail.com
License: Apache
Keywords: replacement template substitute compile
Platform: UNKNOWN
Classifier: Programming Language :: Python :: 3
Classifier: License :: OSI Approved :: Apache Software License
Classifier: Operating System :: OS Independent
Requires-Python: >=3.6
Provides-Extra: dev
